teedoc_plugin_blog/__init__.py
teedoc_plugin_blog/assets/main.js
teedoc_plugin_blog-1.1.6.dist-info/LICENSE
teedoc_plugin_blog-1.1.6.dist-info/METADATA
teedoc_plugin_blog-1.1.6.dist-info/WHEEL
teedoc_plugin_blog-1.1.6.dist-info/top_level.txt
teedoc_plugin_blog-1.1.6.dist-info/RECORD
