Metadata-Version: 2.1
Name: teedoc-plugin-blog
Version: 1.1.6
Summary: blog plugin for teedoc
Home-page: https://github.com/Neutree/teedoc
Author: Neucrack
Author-email: CZD666666@gmail.com
License: MIT
Keywords: doc website markdown jupyter notbook generator teedoc search plugin
Platform: UNKNOWN
Classifier: Intended Audience :: Developers
Classifier: License :: OSI Approved :: MIT License
Classifier: Programming Language :: Python :: 3
Requires-Dist: teedoc-plugin-markdown-parser
